jaeger_bio-1.1.30.data/data/LICENSE
jaeger_bio-1.1.30.data/data/README.md
jaeger_bio-1.1.30.data/scripts/jaeger
jaeger_bio-1.1.30.data/scripts/jaeger_parallel
jaegeraa/__init__.py
jaegeraa/lib.py
jaegeraa/postprocessing.py
jaegeraa/preprocessing.py
jaegeraa/utils.py
jaegeraa/data/LR_ood_3_class.h5
jaegeraa/data/LR_ood_4_class_default.pkl
jaegeraa/data/LR_ood_5_class.h5
jaegeraa/data/WRes_1024.h5
jaegeraa/data/__init__.py
jaegeraa/data/batch_means.npy
jaegeraa/data/batch_std.npy
jaegeraa/data/config.json
jaegeraa/data/simple_amino_res_256_10_3_class.h5
jaegeraa/data/simple_amino_res_256_10_5_class.h5
jaegeraa/data/test_contigs.fasta
jaegeraa/data/test_empty.fasta
jaegeraa/data/test_short.fasta
jaegeraa/nnlib/__init__.py
jaegeraa/nnlib/cmodel.py
jaegeraa/nnlib/layers.py
jaegeraa/v2/preprocessing.py
jaegeraa/v2/nnlib/__init__.py
jaegeraa/v2/nnlib/cmodel.py
jaegeraa/v2/nnlib/layers.py
jaeger_bio-1.1.30.dist-info/LICENSE
jaeger_bio-1.1.30.dist-info/METADATA
jaeger_bio-1.1.30.dist-info/WHEEL
jaeger_bio-1.1.30.dist-info/top_level.txt
jaeger_bio-1.1.30.dist-info/RECORD
