Metadata-Version: 2.1
Name: jaeger-bio
Version: 1.1.30
Summary: A quick and precise pipeline for detecting phages in sequence assemblies.
Home-page: https://github.com/Yasas1994/Jaeger
Author: Yasas Wijesekra
Author-email: yasas.wijesekara@uni-greifswald.de
License: MIT
Classifier: Programming Language :: Python :: 3
Classifier: License :: OSI Approved :: MIT License
Classifier: Natural Language :: English
Classifier: Topic :: Scientific/Engineering :: Bio-Informatics
Classifier: Operating System :: Unix
Requires-Python: >=3.9, <3.12
License-File: LICENSE
Requires-Dist: h5py>=3.8
Requires-Dist: progressbar2>=4.4.2
Requires-Dist: psutil>=5
Requires-Dist: pandas>=1.5
Requires-Dist: kneed>=0.8.5
Requires-Dist: numpy>=1.24
Requires-Dist: ruptures>=1.1.9
Requires-Dist: keras<2.16,>=2.15
Requires-Dist: matplotlib>=3.7
Requires-Dist: scikit-learn==1.3.2
Requires-Dist: parasail==1.3.4
Requires-Dist: pycirclize
Requires-Dist: pyfastx>=2
Provides-Extra: cpu
Requires-Dist: tensorflow<2.16,>=2.15; extra == "cpu"
Provides-Extra: darwin-arm
Requires-Dist: tensorflow<2.16,>=2.15; extra == "darwin-arm"
Requires-Dist: tensorflow-metal; extra == "darwin-arm"
Provides-Extra: gpu
Requires-Dist: tensorflow[and-cuda]<2.16,>=2.15; extra == "gpu"
